MANIFEST.in
README.md
setup.py
datasmoothie/__init__.py
datasmoothie/client.py
datasmoothie/datasource.py
datasmoothie/report.py
datasmoothie.egg-info/PKG-INFO
datasmoothie.egg-info/SOURCES.txt
datasmoothie.egg-info/dependency_links.txt
datasmoothie.egg-info/requires.txt
datasmoothie.egg-info/top_level.txt
datasmoothie/templates/__init__.py
datasmoothie/templates/chart.json