Metadata-Version: 1.1
Name: datasmoothie
Version: 0.12
Summary: Python wrapper for v2 of the Datasmoothie API.
Home-page: https://github.com/datasmoothie/datasmoothie-client-python
Author: Geir Freysson
Author-email: geir@datasmoothie.com
License: MIT
Download-URL: https://github.com/datasmoothie/datasmoothie-client-python/archive/v0.12.tar.gz
Keywords: surveys,market research,weighting,significance tests
Platform: UNKNOWN
Classifier: Programming Language :: Python :: 3
Classifier: License :: OSI Approved :: MIT License
Classifier: Operating System :: OS Independent
